bbeam.cp37-win_amd64.pyd
boxbeam.py
boxbeam-1.3.0.post1.dist-info/LICENSE
boxbeam-1.3.0.post1.dist-info/METADATA
boxbeam-1.3.0.post1.dist-info/WHEEL
boxbeam-1.3.0.post1.dist-info/RECORD
